{
    "calls": [
        {
            "id": "1364175",
            "contract": "ContractTest",
            "function": "testExploit",
            "depth": 0,
            "internal_calls": [
                {
                    "id": "2534",
                    "contract": "0xbb4CdB9CBd36B01bD1cBaEBF2De08d9173bc095c",
                    "function": "balanceOf",
                    "depth": 1,
                    "internal_calls": []
                },
                {
                    "id": "24711",
                    "contract": "0xB75cA3C3e99747d0e2F6e75A9fBD17F5Ac03cebE",
                    "function": "approve",
                    "depth": 1,
                    "internal_calls": []
                },
                {
                    "id": "24562",
                    "contract": "0x55d398326f99059fF775485246999027B3197955",
                    "function": "approve",
                    "depth": 1,
                    "internal_calls": []
                },
                {
                    "id": "24562",
                    "contract": "0x55d398326f99059fF775485246999027B3197955",
                    "function": "approve",
                    "depth": 1,
                    "internal_calls": []
                },
                {
                    "id": "24598",
                    "contract": "0x79cD24Ed4524373aF6e047556018b1440CF04be3",
                    "function": "approve",
                    "depth": 1,
                    "internal_calls": []
                },
                {
                    "id": "24420",
                    "contract": "0xbb4CdB9CBd36B01bD1cBaEBF2De08d9173bc095c",
                    "function": "approve",
                    "depth": 1,
                    "internal_calls": []
                }
            ]
        },
        {
            "id": "534",
            "contract": "0xbb4CdB9CBd36B01bD1cBaEBF2De08d9173bc095c",
            "function": "balanceOf",
            "depth": 1,
            "internal_calls": []
        },
        {
            "id": "76674",
            "contract": "0x10ED43C718714eb63d5aA57B78B54704E256024E",
            "function": "swapExactTokensForTokens",
            "depth": 1,
            "internal_calls": [
                {
                    "id": "2893",
                    "contract": "0x16b9a82891338f9bA80E2D6970FddA79D1eb0daE",
                    "function": "getReserves",
                    "depth": 2,
                    "internal_calls": []
                },
                {
                    "id": "8948",
                    "contract": "0xbb4CdB9CBd36B01bD1cBaEBF2De08d9173bc095c",
                    "function": "transferFrom",
                    "depth": 2,
                    "internal_calls": []
                },
                {
                    "id": "53864",
                    "contract": "0x16b9a82891338f9bA80E2D6970FddA79D1eb0daE",
                    "function": "swap",
                    "depth": 2,
                    "internal_calls": [
                        {
                            "id": "29971",
                            "contract": "0x55d398326f99059fF775485246999027B3197955",
                            "function": "transfer",
                            "depth": 3,
                            "internal_calls": []
                        },
                        {
                            "id": "531",
                            "contract": "0x55d398326f99059fF775485246999027B3197955",
                            "function": "balanceOf",
                            "depth": 3,
                            "internal_calls": []
                        },
                        {
                            "id": "534",
                            "contract": "0xbb4CdB9CBd36B01bD1cBaEBF2De08d9173bc095c",
                            "function": "balanceOf",
                            "depth": 3,
                            "internal_calls": []
                        }
                    ]
                }
            ]
        },
        {
            "id": "531",
            "contract": "0x55d398326f99059fF775485246999027B3197955",
            "function": "balanceOf",
            "depth": 1,
            "internal_calls": []
        },
        {
            "id": "162723",
            "contract": "0x10ED43C718714eb63d5aA57B78B54704E256024E",
            "function": "swapExactTokensForTokens",
            "depth": 1,
            "internal_calls": [
                {
                    "id": "2893",
                    "contract": "0x79cD24Ed4524373aF6e047556018b1440CF04be3",
                    "function": "getReserves",
                    "depth": 2,
                    "internal_calls": []
                },
                {
                    "id": "10834",
                    "contract": "0x55d398326f99059fF775485246999027B3197955",
                    "function": "transferFrom",
                    "depth": 2,
                    "internal_calls": []
                },
                {
                    "id": "140607",
                    "contract": "0x79cD24Ed4524373aF6e047556018b1440CF04be3",
                    "function": "swap",
                    "depth": 2,
                    "internal_calls": [
                        {
                            "id": "104805",
                            "contract": "0xB75cA3C3e99747d0e2F6e75A9fBD17F5Ac03cebE",
                            "function": "transfer",
                            "depth": 3,
                            "internal_calls": [
                                {
                                    "id": "17377",
                                    "contract": "0xfF7A90FA8193b51482c37E84f3E9a0798921380b",
                                    "function": "getDay",
                                    "depth": 4,
                                    "internal_calls": []
                                }
                            ]
                        },
                        {
                            "id": "531",
                            "contract": "0x55d398326f99059fF775485246999027B3197955",
                            "function": "balanceOf",
                            "depth": 3,
                            "internal_calls": []
                        },
                        {
                            "id": "1959",
                            "contract": "0xB75cA3C3e99747d0e2F6e75A9fBD17F5Ac03cebE",
                            "function": "balanceOf",
                            "depth": 3,
                            "internal_calls": []
                        }
                    ]
                }
            ]
        },
        {
            "id": "99250",
            "contract": "0xB75cA3C3e99747d0e2F6e75A9fBD17F5Ac03cebE",
            "function": "tokenAirdrop",
            "depth": 1,
            "internal_calls": [
                {
                    "id": "638",
                    "contract": "0x55d398326f99059fF775485246999027B3197955",
                    "function": "allowance",
                    "depth": 2,
                    "internal_calls": []
                },
                {
                    "id": "10834",
                    "contract": "0x55d398326f99059fF775485246999027B3197955",
                    "function": "transferFrom",
                    "depth": 2,
                    "internal_calls": []
                },
                {
                    "id": "8071",
                    "contract": "0x55d398326f99059fF775485246999027B3197955",
                    "function": "transfer",
                    "depth": 2,
                    "internal_calls": []
                }
            ]
        },
        {
            "id": "531",
            "contract": "0x55d398326f99059fF775485246999027B3197955",
            "function": "balanceOf",
            "depth": 1,
            "internal_calls": []
        },
        {
            "id": "1959",
            "contract": "0xB75cA3C3e99747d0e2F6e75A9fBD17F5Ac03cebE",
            "function": "balanceOf",
            "depth": 1,
            "internal_calls": []
        },
        {
            "id": "176210",
            "contract": "0x10ED43C718714eb63d5aA57B78B54704E256024E",
            "function": "addLiquidity",
            "depth": 1,
            "internal_calls": [
                {
                    "id": "2676",
                    "contract": "0xcA143Ce32Fe78f1f7019d7d551a6402fC5350c73",
                    "function": "getPair",
                    "depth": 2,
                    "internal_calls": []
                },
                {
                    "id": "893",
                    "contract": "0x79cD24Ed4524373aF6e047556018b1440CF04be3",
                    "function": "getReserves",
                    "depth": 2,
                    "internal_calls": []
                },
                {
                    "id": "6034",
                    "contract": "0x55d398326f99059fF775485246999027B3197955",
                    "function": "transferFrom",
                    "depth": 2,
                    "internal_calls": []
                },
                {
                    "id": "77769",
                    "contract": "0xB75cA3C3e99747d0e2F6e75A9fBD17F5Ac03cebE",
                    "function": "transferFrom",
                    "depth": 2,
                    "internal_calls": [
                        {
                            "id": "17377",
                            "contract": "0xfF7A90FA8193b51482c37E84f3E9a0798921380b",
                            "function": "getDay",
                            "depth": 3,
                            "internal_calls": []
                        },
                        {
                            "id": "17377",
                            "contract": "0xfF7A90FA8193b51482c37E84f3E9a0798921380b",
                            "function": "getDay",
                            "depth": 3,
                            "internal_calls": []
                        }
                    ]
                },
                {
                    "id": "79659",
                    "contract": "0x79cD24Ed4524373aF6e047556018b1440CF04be3",
                    "function": "mint",
                    "depth": 2,
                    "internal_calls": [
                        {
                            "id": "531",
                            "contract": "0x55d398326f99059fF775485246999027B3197955",
                            "function": "balanceOf",
                            "depth": 3,
                            "internal_calls": []
                        },
                        {
                            "id": "1959",
                            "contract": "0xB75cA3C3e99747d0e2F6e75A9fBD17F5Ac03cebE",
                            "function": "balanceOf",
                            "depth": 3,
                            "internal_calls": []
                        },
                        {
                            "id": "2354",
                            "contract": "0xcA143Ce32Fe78f1f7019d7d551a6402fC5350c73",
                            "function": "feeTo",
                            "depth": 3,
                            "internal_calls": []
                        }
                    ]
                }
            ]
        },
        {
            "id": "537",
            "contract": "0x79cD24Ed4524373aF6e047556018b1440CF04be3",
            "function": "balanceOf",
            "depth": 1,
            "internal_calls": []
        },
        {
            "id": "66328",
            "contract": "0xB75cA3C3e99747d0e2F6e75A9fBD17F5Ac03cebE",
            "function": "stakeLp",
            "depth": 1,
            "internal_calls": [
                {
                    "id": "655",
                    "contract": "0x79cD24Ed4524373aF6e047556018b1440CF04be3",
                    "function": "allowance",
                    "depth": 2,
                    "internal_calls": []
                },
                {
                    "id": "8376",
                    "contract": "0x79cD24Ed4524373aF6e047556018b1440CF04be3",
                    "function": "transferFrom",
                    "depth": 2,
                    "internal_calls": []
                }
            ]
        },
        {
            "id": "0",
            "contract": "VM",
            "function": "warp",
            "depth": 1,
            "internal_calls": []
        },
        {
            "id": "69120",
            "contract": "0xB75cA3C3e99747d0e2F6e75A9fBD17F5Ac03cebE",
            "function": "claimStakeLp",
            "depth": 1,
            "internal_calls": [
                {
                    "id": "23203",
                    "contract": "0x79cD24Ed4524373aF6e047556018b1440CF04be3",
                    "function": "transfer",
                    "depth": 2,
                    "internal_calls": []
                },
                {
                    "id": "439",
                    "contract": "0x79cD24Ed4524373aF6e047556018b1440CF04be3",
                    "function": "totalSupply",
                    "depth": 2,
                    "internal_calls": []
                },
                {
                    "id": "531",
                    "contract": "0x55d398326f99059fF775485246999027B3197955",
                    "function": "balanceOf",
                    "depth": 2,
                    "internal_calls": []
                },
                {
                    "id": "531",
                    "contract": "0x55d398326f99059fF775485246999027B3197955",
                    "function": "balanceOf",
                    "depth": 2,
                    "internal_calls": []
                },
                {
                    "id": "531",
                    "contract": "0x55d398326f99059fF775485246999027B3197955",
                    "function": "balanceOf",
                    "depth": 2,
                    "internal_calls": []
                }
            ]
        },
        {
            "id": "20354",
            "contract": "0xB75cA3C3e99747d0e2F6e75A9fBD17F5Ac03cebE",
            "function": "claimStakeLp",
            "depth": 1,
            "internal_calls": [
                {
                    "id": "3303",
                    "contract": "0x79cD24Ed4524373aF6e047556018b1440CF04be3",
                    "function": "transfer",
                    "depth": 2,
                    "internal_calls": []
                },
                {
                    "id": "439",
                    "contract": "0x79cD24Ed4524373aF6e047556018b1440CF04be3",
                    "function": "totalSupply",
                    "depth": 2,
                    "internal_calls": []
                },
                {
                    "id": "531",
                    "contract": "0x55d398326f99059fF775485246999027B3197955",
                    "function": "balanceOf",
                    "depth": 2,
                    "internal_calls": []
                },
                {
                    "id": "531",
                    "contract": "0x55d398326f99059fF775485246999027B3197955",
                    "function": "balanceOf",
                    "depth": 2,
                    "internal_calls": []
                },
                {
                    "id": "531",
                    "contract": "0x55d398326f99059fF775485246999027B3197955",
                    "function": "balanceOf",
                    "depth": 2,
                    "internal_calls": []
                }
            ]
        },
        {
            "id": "20354",
            "contract": "0xB75cA3C3e99747d0e2F6e75A9fBD17F5Ac03cebE",
            "function": "claimStakeLp",
            "depth": 1,
            "internal_calls": [
                {
                    "id": "3303",
                    "contract": "0x79cD24Ed4524373aF6e047556018b1440CF04be3",
                    "function": "transfer",
                    "depth": 2,
                    "internal_calls": []
                },
                {
                    "id": "439",
                    "contract": "0x79cD24Ed4524373aF6e047556018b1440CF04be3",
                    "function": "totalSupply",
                    "depth": 2,
                    "internal_calls": []
                },
                {
                    "id": "531",
                    "contract": "0x55d398326f99059fF775485246999027B3197955",
                    "function": "balanceOf",
                    "depth": 2,
                    "internal_calls": []
                },
                {
                    "id": "531",
                    "contract": "0x55d398326f99059fF775485246999027B3197955",
                    "function": "balanceOf",
                    "depth": 2,
                    "internal_calls": []
                },
                {
                    "id": "531",
                    "contract": "0x55d398326f99059fF775485246999027B3197955",
                    "function": "balanceOf",
                    "depth": 2,
                    "internal_calls": []
                }
            ]
        },
        {
            "id": "20354",
            "contract": "0xB75cA3C3e99747d0e2F6e75A9fBD17F5Ac03cebE",
            "function": "claimStakeLp",
            "depth": 1,
            "internal_calls": [
                {
                    "id": "3303",
                    "contract": "0x79cD24Ed4524373aF6e047556018b1440CF04be3",
                    "function": "transfer",
                    "depth": 2,
                    "internal_calls": []
                },
                {
                    "id": "439",
                    "contract": "0x79cD24Ed4524373aF6e047556018b1440CF04be3",
                    "function": "totalSupply",
                    "depth": 2,
                    "internal_calls": []
                },
                {
                    "id": "531",
                    "contract": "0x55d398326f99059fF775485246999027B3197955",
                    "function": "balanceOf",
                    "depth": 2,
                    "internal_calls": []
                },
                {
                    "id": "531",
                    "contract": "0x55d398326f99059fF775485246999027B3197955",
                    "function": "balanceOf",
                    "depth": 2,
                    "internal_calls": []
                },
                {
                    "id": "531",
                    "contract": "0x55d398326f99059fF775485246999027B3197955",
                    "function": "balanceOf",
                    "depth": 2,
                    "internal_calls": []
                }
            ]
        },
        {
            "id": "20354",
            "contract": "0xB75cA3C3e99747d0e2F6e75A9fBD17F5Ac03cebE",
            "function": "claimStakeLp",
            "depth": 1,
            "internal_calls": [
                {
                    "id": "3303",
                    "contract": "0x79cD24Ed4524373aF6e047556018b1440CF04be3",
                    "function": "transfer",
                    "depth": 2,
                    "internal_calls": []
                },
                {
                    "id": "439",
                    "contract": "0x79cD24Ed4524373aF6e047556018b1440CF04be3",
                    "function": "totalSupply",
                    "depth": 2,
                    "internal_calls": []
                },
                {
                    "id": "531",
                    "contract": "0x55d398326f99059fF775485246999027B3197955",
                    "function": "balanceOf",
                    "depth": 2,
                    "internal_calls": []
                },
                {
                    "id": "531",
                    "contract": "0x55d398326f99059fF775485246999027B3197955",
                    "function": "balanceOf",
                    "depth": 2,
                    "internal_calls": []
                },
                {
                    "id": "531",
                    "contract": "0x55d398326f99059fF775485246999027B3197955",
                    "function": "balanceOf",
                    "depth": 2,
                    "internal_calls": []
                }
            ]
        },
        {
            "id": "20354",
            "contract": "0xB75cA3C3e99747d0e2F6e75A9fBD17F5Ac03cebE",
            "function": "claimStakeLp",
            "depth": 1,
            "internal_calls": [
                {
                    "id": "3303",
                    "contract": "0x79cD24Ed4524373aF6e047556018b1440CF04be3",
                    "function": "transfer",
                    "depth": 2,
                    "internal_calls": []
                },
                {
                    "id": "439",
                    "contract": "0x79cD24Ed4524373aF6e047556018b1440CF04be3",
                    "function": "totalSupply",
                    "depth": 2,
                    "internal_calls": []
                },
                {
                    "id": "531",
                    "contract": "0x55d398326f99059fF775485246999027B3197955",
                    "function": "balanceOf",
                    "depth": 2,
                    "internal_calls": []
                },
                {
                    "id": "531",
                    "contract": "0x55d398326f99059fF775485246999027B3197955",
                    "function": "balanceOf",
                    "depth": 2,
                    "internal_calls": []
                },
                {
                    "id": "531",
                    "contract": "0x55d398326f99059fF775485246999027B3197955",
                    "function": "balanceOf",
                    "depth": 2,
                    "internal_calls": []
                }
            ]
        },
        {
            "id": "20354",
            "contract": "0xB75cA3C3e99747d0e2F6e75A9fBD17F5Ac03cebE",
            "function": "claimStakeLp",
            "depth": 1,
            "internal_calls": [
                {
                    "id": "3303",
                    "contract": "0x79cD24Ed4524373aF6e047556018b1440CF04be3",
                    "function": "transfer",
                    "depth": 2,
                    "internal_calls": []
                },
                {
                    "id": "439",
                    "contract": "0x79cD24Ed4524373aF6e047556018b1440CF04be3",
                    "function": "totalSupply",
                    "depth": 2,
                    "internal_calls": []
                },
                {
                    "id": "531",
                    "contract": "0x55d398326f99059fF775485246999027B3197955",
                    "function": "balanceOf",
                    "depth": 2,
                    "internal_calls": []
                },
                {
                    "id": "531",
                    "contract": "0x55d398326f99059fF775485246999027B3197955",
                    "function": "balanceOf",
                    "depth": 2,
                    "internal_calls": []
                },
                {
                    "id": "531",
                    "contract": "0x55d398326f99059fF775485246999027B3197955",
                    "function": "balanceOf",
                    "depth": 2,
                    "internal_calls": []
                }
            ]
        },
        {
            "id": "20354",
            "contract": "0xB75cA3C3e99747d0e2F6e75A9fBD17F5Ac03cebE",
            "function": "claimStakeLp",
            "depth": 1,
            "internal_calls": [
                {
                    "id": "3303",
                    "contract": "0x79cD24Ed4524373aF6e047556018b1440CF04be3",
                    "function": "transfer",
                    "depth": 2,
                    "internal_calls": []
                },
                {
                    "id": "439",
                    "contract": "0x79cD24Ed4524373aF6e047556018b1440CF04be3",
                    "function": "totalSupply",
                    "depth": 2,
                    "internal_calls": []
                },
                {
                    "id": "531",
                    "contract": "0x55d398326f99059fF775485246999027B3197955",
                    "function": "balanceOf",
                    "depth": 2,
                    "internal_calls": []
                },
                {
                    "id": "531",
                    "contract": "0x55d398326f99059fF775485246999027B3197955",
                    "function": "balanceOf",
                    "depth": 2,
                    "internal_calls": []
                },
                {
                    "id": "531",
                    "contract": "0x55d398326f99059fF775485246999027B3197955",
                    "function": "balanceOf",
                    "depth": 2,
                    "internal_calls": []
                }
            ]
        },
        {
            "id": "20354",
            "contract": "0xB75cA3C3e99747d0e2F6e75A9fBD17F5Ac03cebE",
            "function": "claimStakeLp",
            "depth": 1,
            "internal_calls": [
                {
                    "id": "3303",
                    "contract": "0x79cD24Ed4524373aF6e047556018b1440CF04be3",
                    "function": "transfer",
                    "depth": 2,
                    "internal_calls": []
                },
                {
                    "id": "439",
                    "contract": "0x79cD24Ed4524373aF6e047556018b1440CF04be3",
                    "function": "totalSupply",
                    "depth": 2,
                    "internal_calls": []
                },
                {
                    "id": "531",
                    "contract": "0x55d398326f99059fF775485246999027B3197955",
                    "function": "balanceOf",
                    "depth": 2,
                    "internal_calls": []
                },
                {
                    "id": "531",
                    "contract": "0x55d398326f99059fF775485246999027B3197955",
                    "function": "balanceOf",
                    "depth": 2,
                    "internal_calls": []
                },
                {
                    "id": "531",
                    "contract": "0x55d398326f99059fF775485246999027B3197955",
                    "function": "balanceOf",
                    "depth": 2,
                    "internal_calls": []
                }
            ]
        },
        {
            "id": "40411",
            "contract": "0xB75cA3C3e99747d0e2F6e75A9fBD17F5Ac03cebE",
            "function": "claimDpcAirdrop",
            "depth": 1,
            "internal_calls": [
                {
                    "id": "439",
                    "contract": "0x79cD24Ed4524373aF6e047556018b1440CF04be3",
                    "function": "totalSupply",
                    "depth": 2,
                    "internal_calls": []
                },
                {
                    "id": "531",
                    "contract": "0x55d398326f99059fF775485246999027B3197955",
                    "function": "balanceOf",
                    "depth": 2,
                    "internal_calls": []
                },
                {
                    "id": "531",
                    "contract": "0x55d398326f99059fF775485246999027B3197955",
                    "function": "balanceOf",
                    "depth": 2,
                    "internal_calls": []
                },
                {
                    "id": "531",
                    "contract": "0x55d398326f99059fF775485246999027B3197955",
                    "function": "balanceOf",
                    "depth": 2,
                    "internal_calls": []
                }
            ]
        },
        {
            "id": "1959",
            "contract": "0xB75cA3C3e99747d0e2F6e75A9fBD17F5Ac03cebE",
            "function": "balanceOf",
            "depth": 1,
            "internal_calls": []
        },
        {
            "id": "278486",
            "contract": "0x10ED43C718714eb63d5aA57B78B54704E256024E",
            "function": "swapExactTokensForTokensSupportingFeeOnTransferTokens",
            "depth": 1,
            "internal_calls": [
                {
                    "id": "192417",
                    "contract": "0xB75cA3C3e99747d0e2F6e75A9fBD17F5Ac03cebE",
                    "function": "transferFrom",
                    "depth": 2,
                    "internal_calls": [
                        {
                            "id": "18109",
                            "contract": "0xfF7A90FA8193b51482c37E84f3E9a0798921380b",
                            "function": "getDay",
                            "depth": 3,
                            "internal_calls": []
                        },
                        {
                            "id": "18109",
                            "contract": "0xfF7A90FA8193b51482c37E84f3E9a0798921380b",
                            "function": "getDay",
                            "depth": 3,
                            "internal_calls": []
                        },
                        {
                            "id": "18109",
                            "contract": "0xfF7A90FA8193b51482c37E84f3E9a0798921380b",
                            "function": "getDay",
                            "depth": 3,
                            "internal_calls": []
                        },
                        {
                            "id": "18109",
                            "contract": "0xfF7A90FA8193b51482c37E84f3E9a0798921380b",
                            "function": "getDay",
                            "depth": 3,
                            "internal_calls": []
                        }
                    ]
                },
                {
                    "id": "534",
                    "contract": "0xbb4CdB9CBd36B01bD1cBaEBF2De08d9173bc095c",
                    "function": "balanceOf",
                    "depth": 2,
                    "internal_calls": []
                },
                {
                    "id": "893",
                    "contract": "0x79cD24Ed4524373aF6e047556018b1440CF04be3",
                    "function": "getReserves",
                    "depth": 2,
                    "internal_calls": []
                },
                {
                    "id": "1959",
                    "contract": "0xB75cA3C3e99747d0e2F6e75A9fBD17F5Ac03cebE",
                    "function": "balanceOf",
                    "depth": 2,
                    "internal_calls": []
                },
                {
                    "id": "20673",
                    "contract": "0x79cD24Ed4524373aF6e047556018b1440CF04be3",
                    "function": "swap",
                    "depth": 2,
                    "internal_calls": [
                        {
                            "id": "3271",
                            "contract": "0x55d398326f99059fF775485246999027B3197955",
                            "function": "transfer",
                            "depth": 3,
                            "internal_calls": []
                        },
                        {
                            "id": "531",
                            "contract": "0x55d398326f99059fF775485246999027B3197955",
                            "function": "balanceOf",
                            "depth": 3,
                            "internal_calls": []
                        },
                        {
                            "id": "1959",
                            "contract": "0xB75cA3C3e99747d0e2F6e75A9fBD17F5Ac03cebE",
                            "function": "balanceOf",
                            "depth": 3,
                            "internal_calls": []
                        }
                    ]
                },
                {
                    "id": "893",
                    "contract": "0x16b9a82891338f9bA80E2D6970FddA79D1eb0daE",
                    "function": "getReserves",
                    "depth": 2,
                    "internal_calls": []
                },
                {
                    "id": "531",
                    "contract": "0x55d398326f99059fF775485246999027B3197955",
                    "function": "balanceOf",
                    "depth": 2,
                    "internal_calls": []
                },
                {
                    "id": "48739",
                    "contract": "0x16b9a82891338f9bA80E2D6970FddA79D1eb0daE",
                    "function": "swap",
                    "depth": 2,
                    "internal_calls": [
                        {
                            "id": "23162",
                            "contract": "0xbb4CdB9CBd36B01bD1cBaEBF2De08d9173bc095c",
                            "function": "transfer",
                            "depth": 3,
                            "internal_calls": []
                        },
                        {
                            "id": "531",
                            "contract": "0x55d398326f99059fF775485246999027B3197955",
                            "function": "balanceOf",
                            "depth": 3,
                            "internal_calls": []
                        },
                        {
                            "id": "534",
                            "contract": "0xbb4CdB9CBd36B01bD1cBaEBF2De08d9173bc095c",
                            "function": "balanceOf",
                            "depth": 3,
                            "internal_calls": []
                        }
                    ]
                },
                {
                    "id": "534",
                    "contract": "0xbb4CdB9CBd36B01bD1cBaEBF2De08d9173bc095c",
                    "function": "balanceOf",
                    "depth": 2,
                    "internal_calls": []
                }
            ]
        },
        {
            "id": "534",
            "contract": "0xbb4CdB9CBd36B01bD1cBaEBF2De08d9173bc095c",
            "function": "balanceOf",
            "depth": 1,
            "internal_calls": []
        }
    ]
}