{
    "calls": [
        {
            "id": "2968554",
            "contract": "PredyFinance",
            "function": "testExploit",
            "depth": 0,
            "internal_calls": [
                {
                    "id": "10281",
                    "contract": "USDC",
                    "function": "symbol",
                    "depth": 1,
                    "internal_calls": [
                        {
                            "id": "3081",
                            "contract": "0x86E721b43d4ECFa71119Dd38c0f938A75Fdb57B3",
                            "function": "symbol",
                            "depth": 2,
                            "internal_calls": []
                        }
                    ]
                },
                {
                    "id": "3250",
                    "contract": "USDC",
                    "function": "balanceOf",
                    "depth": 1,
                    "internal_calls": [
                        {
                            "id": "2553",
                            "contract": "0x86E721b43d4ECFa71119Dd38c0f938A75Fdb57B3",
                            "function": "balanceOf",
                            "depth": 2,
                            "internal_calls": []
                        }
                    ]
                },
                {
                    "id": "3043",
                    "contract": "USDC",
                    "function": "decimals",
                    "depth": 1,
                    "internal_calls": [
                        {
                            "id": "2381",
                            "contract": "0x86E721b43d4ECFa71119Dd38c0f938A75Fdb57B3",
                            "function": "decimals",
                            "depth": 2,
                            "internal_calls": []
                        }
                    ]
                },
                {
                    "id": "27341",
                    "contract": "USDC",
                    "function": "approve",
                    "depth": 1,
                    "internal_calls": [
                        {
                            "id": "26673",
                            "contract": "0x86E721b43d4ECFa71119Dd38c0f938A75Fdb57B3",
                            "function": "approve",
                            "depth": 2,
                            "internal_calls": []
                        }
                    ]
                },
                {
                    "id": "31808",
                    "contract": "WETH",
                    "function": "approve",
                    "depth": 1,
                    "internal_calls": [
                        {
                            "id": "24562",
                            "contract": "0x8b194bEae1d3e0788A1a35173978001ACDFba668",
                            "function": "approve",
                            "depth": 2,
                            "internal_calls": []
                        }
                    ]
                },
                {
                    "id": "2064742",
                    "contract": "PredyPool",
                    "function": "registerPair",
                    "depth": 1,
                    "internal_calls": [
                        {
                            "id": "2059697",
                            "contract": "0x7b8b944AB2f24C829504a7a6D70fce5298f2147c",
                            "function": "registerPair",
                            "depth": 2,
                            "internal_calls": [
                                {
                                    "id": "2053417",
                                    "contract": "0x2D756f7912B5c61f35ca3E5b310C7C133A90977c",
                                    "function": "ac826482",
                                    "depth": 3,
                                    "internal_calls": [
                                        {
                                            "id": "266",
                                            "contract": "0xC6962004f452bE9203591991D15f6b388e09E8D0",
                                            "function": "token0",
                                            "depth": 4,
                                            "internal_calls": []
                                        },
                                        {
                                            "id": "308",
                                            "contract": "0xC6962004f452bE9203591991D15f6b388e09E8D0",
                                            "function": "token1",
                                            "depth": 4,
                                            "internal_calls": []
                                        },
                                        {
                                            "id": "251",
                                            "contract": "0xC6962004f452bE9203591991D15f6b388e09E8D0",
                                            "function": "fee",
                                            "depth": 4,
                                            "internal_calls": []
                                        },
                                        {
                                            "id": "2666",
                                            "contract": "0x1F98431c8aD98523631AE4a59f267346ea31F984",
                                            "function": "getPool",
                                            "depth": 4,
                                            "internal_calls": []
                                        },
                                        {
                                            "id": "266",
                                            "contract": "0xC6962004f452bE9203591991D15f6b388e09E8D0",
                                            "function": "token0",
                                            "depth": 4,
                                            "internal_calls": []
                                        },
                                        {
                                            "id": "266",
                                            "contract": "0xC6962004f452bE9203591991D15f6b388e09E8D0",
                                            "function": "token0",
                                            "depth": 4,
                                            "internal_calls": []
                                        },
                                        {
                                            "id": "308",
                                            "contract": "0xC6962004f452bE9203591991D15f6b388e09E8D0",
                                            "function": "token1",
                                            "depth": 4,
                                            "internal_calls": []
                                        },
                                        {
                                            "id": "3785",
                                            "contract": "WETH",
                                            "function": "name",
                                            "depth": 4,
                                            "internal_calls": [
                                                {
                                                    "id": "3039",
                                                    "contract": "0x8b194bEae1d3e0788A1a35173978001ACDFba668",
                                                    "function": "name",
                                                    "depth": 5,
                                                    "internal_calls": []
                                                }
                                            ]
                                        },
                                        {
                                            "id": "3850",
                                            "contract": "WETH",
                                            "function": "symbol",
                                            "depth": 4,
                                            "internal_calls": [
                                                {
                                                    "id": "3104",
                                                    "contract": "0x8b194bEae1d3e0788A1a35173978001ACDFba668",
                                                    "function": "symbol",
                                                    "depth": 5,
                                                    "internal_calls": []
                                                }
                                            ]
                                        },
                                        {
                                            "id": "3076",
                                            "contract": "WETH",
                                            "function": "decimals",
                                            "depth": 4,
                                            "internal_calls": [
                                                {
                                                    "id": "2336",
                                                    "contract": "0x8b194bEae1d3e0788A1a35173978001ACDFba668",
                                                    "function": "decimals",
                                                    "depth": 5,
                                                    "internal_calls": []
                                                }
                                            ]
                                        },
                                        {
                                            "id": "686767",
                                            "contract": "\u2192 new <unknown>@0x3Dd636919d4180B59d9225370CB84F1BA849aba2",
                                            "function": "constructor",
                                            "depth": 4,
                                            "internal_calls": []
                                        },
                                        {
                                            "id": "3729",
                                            "contract": "USDC",
                                            "function": "name",
                                            "depth": 4,
                                            "internal_calls": [
                                                {
                                                    "id": "3061",
                                                    "contract": "0x86E721b43d4ECFa71119Dd38c0f938A75Fdb57B3",
                                                    "function": "name",
                                                    "depth": 5,
                                                    "internal_calls": []
                                                }
                                            ]
                                        },
                                        {
                                            "id": "1781",
                                            "contract": "USDC",
                                            "function": "symbol",
                                            "depth": 4,
                                            "internal_calls": [
                                                {
                                                    "id": "1081",
                                                    "contract": "0x86E721b43d4ECFa71119Dd38c0f938A75Fdb57B3",
                                                    "function": "symbol",
                                                    "depth": 5,
                                                    "internal_calls": []
                                                }
                                            ]
                                        },
                                        {
                                            "id": "1043",
                                            "contract": "USDC",
                                            "function": "decimals",
                                            "depth": 4,
                                            "internal_calls": [
                                                {
                                                    "id": "381",
                                                    "contract": "0x86E721b43d4ECFa71119Dd38c0f938A75Fdb57B3",
                                                    "function": "decimals",
                                                    "depth": 5,
                                                    "internal_calls": []
                                                }
                                            ]
                                        },
                                        {
                                            "id": "686767",
                                            "contract": "\u2192 new <unknown>@0x0b9F4DFb6eB2A8c2F26E98C4538422E6b8C4599F",
                                            "function": "constructor",
                                            "depth": 4,
                                            "internal_calls": []
                                        }
                                    ]
                                }
                            ]
                        }
                    ]
                },
                {
                    "id": "678119",
                    "contract": "PredyPool",
                    "function": "trade",
                    "depth": 1,
                    "internal_calls": [
                        {
                            "id": "677580",
                            "contract": "0x7b8b944AB2f24C829504a7a6D70fce5298f2147c",
                            "function": "trade",
                            "depth": 2,
                            "internal_calls": [
                                {
                                    "id": "552535",
                                    "contract": "0xdE12Aa19734DaCbd34CeDdE14F8290a70A85537f",
                                    "function": "95629036",
                                    "depth": 3,
                                    "internal_calls": [
                                        {
                                            "id": "118261",
                                            "contract": "0x8D9Eb354B3858E9E93be3ffc8b2A98732804383C",
                                            "function": "95629036",
                                            "depth": 4,
                                            "internal_calls": [
                                                {
                                                    "id": "2696",
                                                    "contract": "0xC6962004f452bE9203591991D15f6b388e09E8D0",
                                                    "function": "slot0",
                                                    "depth": 5,
                                                    "internal_calls": []
                                                },
                                                {
                                                    "id": "696",
                                                    "contract": "0xC6962004f452bE9203591991D15f6b388e09E8D0",
                                                    "function": "slot0",
                                                    "depth": 5,
                                                    "internal_calls": []
                                                },
                                                {
                                                    "id": "2364",
                                                    "contract": "0xC6962004f452bE9203591991D15f6b388e09E8D0",
                                                    "function": "feeGrowthGlobal0X128",
                                                    "depth": 5,
                                                    "internal_calls": []
                                                },
                                                {
                                                    "id": "2388",
                                                    "contract": "0xC6962004f452bE9203591991D15f6b388e09E8D0",
                                                    "function": "feeGrowthGlobal1X128",
                                                    "depth": 5,
                                                    "internal_calls": []
                                                },
                                                {
                                                    "id": "9199",
                                                    "contract": "0xC6962004f452bE9203591991D15f6b388e09E8D0",
                                                    "function": "ticks",
                                                    "depth": 5,
                                                    "internal_calls": []
                                                },
                                                {
                                                    "id": "9199",
                                                    "contract": "0xC6962004f452bE9203591991D15f6b388e09E8D0",
                                                    "function": "ticks",
                                                    "depth": 5,
                                                    "internal_calls": []
                                                }
                                            ]
                                        },
                                        {
                                            "id": "421",
                                            "contract": "PredyFinance",
                                            "function": "getSqrtPrice",
                                            "depth": 4,
                                            "internal_calls": []
                                        },
                                        {
                                            "id": "3296",
                                            "contract": "WETH",
                                            "function": "balanceOf",
                                            "depth": 4,
                                            "internal_calls": [
                                                {
                                                    "id": "2553",
                                                    "contract": "0x8b194bEae1d3e0788A1a35173978001ACDFba668",
                                                    "function": "balanceOf",
                                                    "depth": 5,
                                                    "internal_calls": []
                                                }
                                            ]
                                        },
                                        {
                                            "id": "3250",
                                            "contract": "USDC",
                                            "function": "balanceOf",
                                            "depth": 4,
                                            "internal_calls": [
                                                {
                                                    "id": "2553",
                                                    "contract": "0x86E721b43d4ECFa71119Dd38c0f938A75Fdb57B3",
                                                    "function": "balanceOf",
                                                    "depth": 5,
                                                    "internal_calls": []
                                                }
                                            ]
                                        },
                                        {
                                            "id": "267331",
                                            "contract": "PredyFinance",
                                            "function": "predyTradeAfterCallback",
                                            "depth": 4,
                                            "internal_calls": [
                                                {
                                                    "id": "1296",
                                                    "contract": "WETH",
                                                    "function": "balanceOf",
                                                    "depth": 5,
                                                    "internal_calls": [
                                                        {
                                                            "id": "553",
                                                            "contract": "0x8b194bEae1d3e0788A1a35173978001ACDFba668",
                                                            "function": "balanceOf",
                                                            "depth": 6,
                                                            "internal_calls": []
                                                        }
                                                    ]
                                                },
                                                {
                                                    "id": "40624",
                                                    "contract": "PredyPool",
                                                    "function": "take",
                                                    "depth": 5,
                                                    "internal_calls": [
                                                        {
                                                            "id": "40163",
                                                            "contract": "0x7b8b944AB2f24C829504a7a6D70fce5298f2147c",
                                                            "function": "take",
                                                            "depth": 6,
                                                            "internal_calls": [
                                                                {
                                                                    "id": "28900",
                                                                    "contract": "WETH",
                                                                    "function": "transfer",
                                                                    "depth": 7,
                                                                    "internal_calls": [
                                                                        {
                                                                            "id": "28154",
                                                                            "contract": "0x8b194bEae1d3e0788A1a35173978001ACDFba668",
                                                                            "function": "transfer",
                                                                            "depth": 8,
                                                                            "internal_calls": []
                                                                        }
                                                                    ]
                                                                }
                                                            ]
                                                        }
                                                    ]
                                                },
                                                {
                                                    "id": "1296",
                                                    "contract": "WETH",
                                                    "function": "balanceOf",
                                                    "depth": 5,
                                                    "internal_calls": [
                                                        {
                                                            "id": "553",
                                                            "contract": "0x8b194bEae1d3e0788A1a35173978001ACDFba668",
                                                            "function": "balanceOf",
                                                            "depth": 6,
                                                            "internal_calls": []
                                                        }
                                                    ]
                                                },
                                                {
                                                    "id": "87373",
                                                    "contract": "PredyPool",
                                                    "function": "supply",
                                                    "depth": 5,
                                                    "internal_calls": [
                                                        {
                                                            "id": "86909",
                                                            "contract": "0x7b8b944AB2f24C829504a7a6D70fce5298f2147c",
                                                            "function": "supply",
                                                            "depth": 6,
                                                            "internal_calls": [
                                                                {
                                                                    "id": "78373",
                                                                    "contract": "0x5E8d28Bd2abE77e9D3e9DD8CCc1727EDa616ACE0",
                                                                    "function": "3ec463bf",
                                                                    "depth": 7,
                                                                    "internal_calls": [
                                                                        {
                                                                            "id": "6880",
                                                                            "contract": "WETH",
                                                                            "function": "transferFrom",
                                                                            "depth": 8,
                                                                            "internal_calls": [
                                                                                {
                                                                                    "id": "6128",
                                                                                    "contract": "0x8b194bEae1d3e0788A1a35173978001ACDFba668",
                                                                                    "function": "transferFrom",
                                                                                    "depth": 9,
                                                                                    "internal_calls": []
                                                                                }
                                                                            ]
                                                                        },
                                                                        {
                                                                            "id": "46736",
                                                                            "contract": "0x3Dd636919d4180B59d9225370CB84F1BA849aba2",
                                                                            "function": "mint",
                                                                            "depth": 8,
                                                                            "internal_calls": []
                                                                        }
                                                                    ]
                                                                }
                                                            ]
                                                        }
                                                    ]
                                                },
                                                {
                                                    "id": "1250",
                                                    "contract": "USDC",
                                                    "function": "balanceOf",
                                                    "depth": 5,
                                                    "internal_calls": [
                                                        {
                                                            "id": "553",
                                                            "contract": "0x86E721b43d4ECFa71119Dd38c0f938A75Fdb57B3",
                                                            "function": "balanceOf",
                                                            "depth": 6,
                                                            "internal_calls": []
                                                        }
                                                    ]
                                                },
                                                {
                                                    "id": "39777",
                                                    "contract": "PredyPool",
                                                    "function": "take",
                                                    "depth": 5,
                                                    "internal_calls": [
                                                        {
                                                            "id": "39316",
                                                            "contract": "0x7b8b944AB2f24C829504a7a6D70fce5298f2147c",
                                                            "function": "take",
                                                            "depth": 6,
                                                            "internal_calls": [
                                                                {
                                                                    "id": "28063",
                                                                    "contract": "USDC",
                                                                    "function": "transfer",
                                                                    "depth": 7,
                                                                    "internal_calls": [
                                                                        {
                                                                            "id": "27363",
                                                                            "contract": "0x86E721b43d4ECFa71119Dd38c0f938A75Fdb57B3",
                                                                            "function": "transfer",
                                                                            "depth": 8,
                                                                            "internal_calls": []
                                                                        }
                                                                    ]
                                                                }
                                                            ]
                                                        }
                                                    ]
                                                },
                                                {
                                                    "id": "1250",
                                                    "contract": "USDC",
                                                    "function": "balanceOf",
                                                    "depth": 5,
                                                    "internal_calls": [
                                                        {
                                                            "id": "553",
                                                            "contract": "0x86E721b43d4ECFa71119Dd38c0f938A75Fdb57B3",
                                                            "function": "balanceOf",
                                                            "depth": 6,
                                                            "internal_calls": []
                                                        }
                                                    ]
                                                },
                                                {
                                                    "id": "82411",
                                                    "contract": "PredyPool",
                                                    "function": "supply",
                                                    "depth": 5,
                                                    "internal_calls": [
                                                        {
                                                            "id": "81947",
                                                            "contract": "0x7b8b944AB2f24C829504a7a6D70fce5298f2147c",
                                                            "function": "supply",
                                                            "depth": 6,
                                                            "internal_calls": [
                                                                {
                                                                    "id": "77911",
                                                                    "contract": "0x5E8d28Bd2abE77e9D3e9DD8CCc1727EDa616ACE0",
                                                                    "function": "3ec463bf",
                                                                    "depth": 7,
                                                                    "internal_calls": [
                                                                        {
                                                                            "id": "6428",
                                                                            "contract": "USDC",
                                                                            "function": "transferFrom",
                                                                            "depth": 8,
                                                                            "internal_calls": [
                                                                                {
                                                                                    "id": "5754",
                                                                                    "contract": "0x86E721b43d4ECFa71119Dd38c0f938A75Fdb57B3",
                                                                                    "function": "transferFrom",
                                                                                    "depth": 9,
                                                                                    "internal_calls": []
                                                                                }
                                                                            ]
                                                                        },
                                                                        {
                                                                            "id": "46736",
                                                                            "contract": "0x0b9F4DFb6eB2A8c2F26E98C4538422E6b8C4599F",
                                                                            "function": "mint",
                                                                            "depth": 8,
                                                                            "internal_calls": []
                                                                        }
                                                                    ]
                                                                }
                                                            ]
                                                        }
                                                    ]
                                                }
                                            ]
                                        },
                                        {
                                            "id": "1296",
                                            "contract": "WETH",
                                            "function": "balanceOf",
                                            "depth": 4,
                                            "internal_calls": [
                                                {
                                                    "id": "553",
                                                    "contract": "0x8b194bEae1d3e0788A1a35173978001ACDFba668",
                                                    "function": "balanceOf",
                                                    "depth": 5,
                                                    "internal_calls": []
                                                }
                                            ]
                                        },
                                        {
                                            "id": "1250",
                                            "contract": "USDC",
                                            "function": "balanceOf",
                                            "depth": 4,
                                            "internal_calls": [
                                                {
                                                    "id": "553",
                                                    "contract": "0x86E721b43d4ECFa71119Dd38c0f938A75Fdb57B3",
                                                    "function": "balanceOf",
                                                    "depth": 5,
                                                    "internal_calls": []
                                                }
                                            ]
                                        },
                                        {
                                            "id": "421",
                                            "contract": "PredyFinance",
                                            "function": "getSqrtPrice",
                                            "depth": 4,
                                            "internal_calls": []
                                        }
                                    ]
                                }
                            ]
                        }
                    ]
                },
                {
                    "id": "1296",
                    "contract": "WETH",
                    "function": "balanceOf",
                    "depth": 1,
                    "internal_calls": [
                        {
                            "id": "553",
                            "contract": "0x8b194bEae1d3e0788A1a35173978001ACDFba668",
                            "function": "balanceOf",
                            "depth": 2,
                            "internal_calls": []
                        }
                    ]
                },
                {
                    "id": "41654",
                    "contract": "PredyPool",
                    "function": "withdraw",
                    "depth": 1,
                    "internal_calls": [
                        {
                            "id": "41187",
                            "contract": "0x7b8b944AB2f24C829504a7a6D70fce5298f2147c",
                            "function": "withdraw",
                            "depth": 2,
                            "internal_calls": [
                                {
                                    "id": "37044",
                                    "contract": "0x5E8d28Bd2abE77e9D3e9DD8CCc1727EDa616ACE0",
                                    "function": "3e16468d",
                                    "depth": 3,
                                    "internal_calls": [
                                        {
                                            "id": "542",
                                            "contract": "0x3Dd636919d4180B59d9225370CB84F1BA849aba2",
                                            "function": "balanceOf",
                                            "depth": 4,
                                            "internal_calls": []
                                        },
                                        {
                                            "id": "2913",
                                            "contract": "0x3Dd636919d4180B59d9225370CB84F1BA849aba2",
                                            "function": "burn",
                                            "depth": 4,
                                            "internal_calls": []
                                        },
                                        {
                                            "id": "26900",
                                            "contract": "WETH",
                                            "function": "transfer",
                                            "depth": 4,
                                            "internal_calls": [
                                                {
                                                    "id": "26154",
                                                    "contract": "0x8b194bEae1d3e0788A1a35173978001ACDFba668",
                                                    "function": "transfer",
                                                    "depth": 5,
                                                    "internal_calls": []
                                                }
                                            ]
                                        }
                                    ]
                                }
                            ]
                        }
                    ]
                },
                {
                    "id": "1250",
                    "contract": "USDC",
                    "function": "balanceOf",
                    "depth": 1,
                    "internal_calls": [
                        {
                            "id": "553",
                            "contract": "0x86E721b43d4ECFa71119Dd38c0f938A75Fdb57B3",
                            "function": "balanceOf",
                            "depth": 2,
                            "internal_calls": []
                        }
                    ]
                },
                {
                    "id": "42807",
                    "contract": "PredyPool",
                    "function": "withdraw",
                    "depth": 1,
                    "internal_calls": [
                        {
                            "id": "42340",
                            "contract": "0x7b8b944AB2f24C829504a7a6D70fce5298f2147c",
                            "function": "withdraw",
                            "depth": 2,
                            "internal_calls": [
                                {
                                    "id": "38197",
                                    "contract": "0x5E8d28Bd2abE77e9D3e9DD8CCc1727EDa616ACE0",
                                    "function": "3e16468d",
                                    "depth": 3,
                                    "internal_calls": [
                                        {
                                            "id": "542",
                                            "contract": "0x0b9F4DFb6eB2A8c2F26E98C4538422E6b8C4599F",
                                            "function": "balanceOf",
                                            "depth": 4,
                                            "internal_calls": []
                                        },
                                        {
                                            "id": "2913",
                                            "contract": "0x0b9F4DFb6eB2A8c2F26E98C4538422E6b8C4599F",
                                            "function": "burn",
                                            "depth": 4,
                                            "internal_calls": []
                                        },
                                        {
                                            "id": "28063",
                                            "contract": "USDC",
                                            "function": "transfer",
                                            "depth": 4,
                                            "internal_calls": [
                                                {
                                                    "id": "27363",
                                                    "contract": "0x86E721b43d4ECFa71119Dd38c0f938A75Fdb57B3",
                                                    "function": "transfer",
                                                    "depth": 5,
                                                    "internal_calls": []
                                                }
                                            ]
                                        }
                                    ]
                                }
                            ]
                        }
                    ]
                },
                {
                    "id": "1781",
                    "contract": "USDC",
                    "function": "symbol",
                    "depth": 1,
                    "internal_calls": [
                        {
                            "id": "1081",
                            "contract": "0x86E721b43d4ECFa71119Dd38c0f938A75Fdb57B3",
                            "function": "symbol",
                            "depth": 2,
                            "internal_calls": []
                        }
                    ]
                },
                {
                    "id": "1250",
                    "contract": "USDC",
                    "function": "balanceOf",
                    "depth": 1,
                    "internal_calls": [
                        {
                            "id": "553",
                            "contract": "0x86E721b43d4ECFa71119Dd38c0f938A75Fdb57B3",
                            "function": "balanceOf",
                            "depth": 2,
                            "internal_calls": []
                        }
                    ]
                },
                {
                    "id": "1043",
                    "contract": "USDC",
                    "function": "decimals",
                    "depth": 1,
                    "internal_calls": [
                        {
                            "id": "381",
                            "contract": "0x86E721b43d4ECFa71119Dd38c0f938A75Fdb57B3",
                            "function": "decimals",
                            "depth": 2,
                            "internal_calls": []
                        }
                    ]
                }
            ]
        }
    ]
}